lsl_cli/__init__.py
lsl_cli/delay.py
lsl_cli/echo.py
lsl_cli/find.py
lsl_cli/list.py
lsl_cli/lsl.py
lsl_cli/rate.py
lsl_cli/show.py
lsl_cli/stub.py
lsl_cli/utils.py
lsl_cli/xdf.py
lsl_cli/extra/lsl-completion.bash
lsl_cli/extra/lsl-completion.zsh
lsl_cli/extra/lsl_complete_script.sh
lsl_cli-0.1.3.dist-info/LICENSE
lsl_cli-0.1.3.dist-info/METADATA
lsl_cli-0.1.3.dist-info/WHEEL
lsl_cli-0.1.3.dist-info/entry_points.txt
lsl_cli-0.1.3.dist-info/top_level.txt
lsl_cli-0.1.3.dist-info/RECORD
