Metadata-Version: 2.1
Name: lsl-cli
Version: 0.1.3
Summary: Command-line tools for the Lab Streaming Layer.
Home-page: https://github.com/yop0/lsl-cli
Author: Johan Medrano
Author-email: johan.medrano653@gmail.com
License: MIT
Platform: UNKNOWN
Classifier: Development Status :: 1 - Planning
License-File: LICENSE
Requires-Dist: pylsl
Requires-Dist: pyxdf
